{
  "db_name": "MySQL",
  "query": "SELECT * FROM word a where a.value like ?",
  "describe": {
    "columns": [
      {
        "ordinal": 0,
        "name": "id",
        "type_info": {
          "type": "Long",
          "flags": "NOT_NULL | PRIMARY_KEY | UNSIGNED | AUTO_INCREMENT",
          "char_set": 63,
          "max_size": 10
        }
      },
      {
        "ordinal": 1,
        "name": "value",
        "type_info": {
          "type": "VarString",
          "flags": "NOT_NULL | NO_DEFAULT_VALUE",
          "char_set": 224,
          "max_size": 400
        }
      },
      {
        "ordinal": 2,
        "name": "lang",
        "type_info": {
          "type": "VarString",
          "flags": "NOT_NULL | NO_DEFAULT_VALUE",
          "char_set": 224,
          "max_size": 12
        }
      }
    ],
    "parameters": {
      "Right": 1
    },
    "nullable": [
      false,
      false,
      false
    ]
  },
  "hash": "4f3d3f98cc2b8f338d3643fa7d5b3315c7854c738118b9986a3dbdad766c07ed"
}
